<WineReviews>
	<Countries>
		<Country id="country_45" name="Italy">
			<Region id="region_1238" region="Etna" province="Sicily &amp; Sardinia" lat="37.7510251" lon="14.9940321"/>
			<Region id="region_1243" region="Vittoria" province="Sicily &amp; Sardinia" lat="36.9514957" lon="14.5304867"/>
		</Country>
		<Country id="country_46" name="Portugal">
			<Region id="region_1239" region="" province="Douro" lat="39.6621648" lon="-8.1353519"/>
		</Country>
		<Country id="country_47" name="US">
			<Region id="region_1240" region="Willamette Valley" province="Oregon" lat="44.67443045" lon="-123.05774148227209"/>
			<Region id="region_1241" region="Lake Michigan Shore" province="Michigan" lat="0" lon="0"/>
			<Region id="region_1245" region="Napa Valley" province="California" lat="38.84847025" lon="-94.4130930172303"/>
			<Region id="region_1246" region="Alexander Valley" province="California" lat="38.6712308" lon="-122.8278697"/>
			<Region id="region_1247" region="Central Coast" province="California" lat="0" lon="0"/>
		</Country>
		<Country id="country_48" name="Spain">
			<Region id="region_1242" region="Navarra" province="Northern Spain" lat="42.54084" lon="0.0316563"/>
		</Country>
		<Country id="country_49" name="France">
			<Region id="region_1244" region="Alsace" province="Alsace" lat="48.24917645" lon="7.4074699518555"/>
		</Country>
		<Country id="country_50" name="Germany"/>
	</Countries>
	<Wines>
		<Wine id="wine_85773" price="15.0" designation="Vulkà Bianco" country_id="country_45" region_id="region_1238" variaty="White Blend" winery="Nicosia"/>
		<Wine id="wine_85774" price="15.0" designation="Avidagos" country_id="country_46" region_id="region_1239" variaty="Portuguese Red" winery="Quinta dos Avidagos"/>
		<Wine id="wine_85775" price="14.0" designation="" country_id="country_47" region_id="region_1240" variaty="Pinot Gris" winery="Rainstorm"/>
		<Wine id="wine_85776" price="13.0" designation="Reserve Late Harvest" country_id="country_47" region_id="region_1241" variaty="Riesling" winery="St. Julian"/>
		<Wine id="wine_85777" price="65.0" designation="Vintner's Reserve Wild Child Block" country_id="country_47" region_id="region_1240" variaty="Pinot Noir" winery="Sweet Cheeks"/>
		<Wine id="wine_85778" price="15.0" designation="Ars In Vitro" country_id="country_48" region_id="region_1242" variaty="Tempranillo-Merlot" winery="Tandem"/>
		<Wine id="wine_85779" price="16.0" designation="Belsito" country_id="country_45" region_id="region_1243" variaty="Frappato" winery="Terre di Giurfo"/>
		<Wine id="wine_85780" price="24.0" designation="" country_id="country_49" region_id="region_1244" variaty="Gewürztraminer" winery="Trimbach"/>
		<Wine id="wine_85781" price="12.0" designation="Shine" country_id="country_50" region_id="region_1239" variaty="Gewürztraminer" winery="Heinz Eifel"/>
		<Wine id="wine_85782" price="27.0" designation="Les Natures" country_id="country_49" region_id="region_1244" variaty="Pinot Gris" winery="Jean-Baptiste Adam"/>
		<Wine id="wine_85783" price="19.0" designation="Mountain Cuvée" country_id="country_47" region_id="region_1245" variaty="Cabernet Sauvignon" winery="Kirkland Signature"/>
		<Wine id="wine_85784" price="30.0" designation="" country_id="country_49" region_id="region_1244" variaty="Gewürztraminer" winery="Leon Beyer"/>
		<Wine id="wine_85785" price="34.0" designation="" country_id="country_47" region_id="region_1246" variaty="Cabernet Sauvignon" winery="Louis M. Martini"/>
		<Wine id="wine_85786" price="12.0" designation="Rosso" country_id="country_45" region_id="region_1238" variaty="Nerello Mascalese" winery="Masseria Setteporte"/>
		<Wine id="wine_85787" price="12.0" designation="" country_id="country_47" region_id="region_1247" variaty="Chardonnay" winery="Mirassou"/>
	</Wines>
	<Tasters>
		<Taster id="taster_21" name="Kerin O’Keefe" twitter_handle="@kerinokeefe"/>
		<Taster id="taster_22" name="Roger Voss" twitter_handle="@vossroger"/>
		<Taster id="taster_23" name="Paul Gregutt" twitter_handle="@paulgwine "/>
		<Taster id="taster_24" name="Alexander Peartree" twitter_handle=""/>
		<Taster id="taster_25" name="Michael Schachner" twitter_handle="@wineschach"/>
		<Taster id="taster_26" name="Anna Lee C. Iijima" twitter_handle=""/>
		<Taster id="taster_27" name="Virginie Boone" twitter_handle="@vboone"/>
		<Taster id="taster_28" name="Matt Kettmann" twitter_handle="@mattkettmann"/>
	</Tasters>
	<Reviews>
		<Review id="review_119979" taster_id="taster_21" wine_id="wine_85773" points="87">
			<ReviewDescription>Aromas include tropical fruit, broom, brimstone and dried herb. The palate isn't overly expressive, offering unripened apple, citrus and dried sage alongside brisk acidity.</ReviewDescription>
		</Review>
		<Review id="review_119980" taster_id="taster_22" wine_id="wine_85774" points="87">
			<ReviewDescription>This is ripe and fruity, a wine that is smooth while still structured. Firm tannins are filled out with juicy red berry fruits and freshened with acidity. It's  already drinkable, although it will certainly be better from 2016.</ReviewDescription>
		</Review>
		<Review id="review_119981" taster_id="taster_23" wine_id="wine_85775" points="87">
			<ReviewDescription>Tart and snappy, the flavors of lime flesh and rind dominate. Some green pineapple pokes through, with crisp acidity underscoring the flavors. The wine was all stainless-steel fermented.</ReviewDescription>
		</Review>
		<Review id="review_119982" taster_id="taster_24" wine_id="wine_85776" points="87">
			<ReviewDescription>Pineapple rind, lemon pith and orange blossom start off the aromas. The palate is a bit more opulent, with notes of honey-drizzled guava and mango giving way to a slightly astringent, semidry finish.</ReviewDescription>
		</Review>
		<Review id="review_119983" taster_id="taster_23" wine_id="wine_85777" points="87">
			<ReviewDescription>Much like the regular bottling from 2012, this comes across as rather rough and tannic, with rustic, earthy, herbal characteristics. Nonetheless, if you think of it as a pleasantly unfussy country wine, it's a good companion to a hearty winter stew.</ReviewDescription>
		</Review>
		<Review id="review_119984" taster_id="taster_25" wine_id="wine_85778" points="87">
			<ReviewDescription>Blackberry and raspberry aromas show a typical Navarran whiff of green herbs and, in this case, horseradish. In the mouth, this is fairly full bodied, with tomatoey acidity. Spicy, herbal flavors complement dark plum fruit, while the finish is fresh but grabby.</ReviewDescription>
		</Review>
		<Review id="review_119985" taster_id="taster_21" wine_id="wine_85779" points="87">
			<ReviewDescription>Here's a bright, informal red that opens with aromas of candied berry, white pepper and savory herb that carry over to the palate. It's balanced with fresh acidity and soft tannins.</ReviewDescription>
		</Review>
		<Review id="review_119986" taster_id="taster_22" wine_id="wine_85780" points="87">
			<ReviewDescription>This dry and restrained wine offers spice in profusion. Balanced with acidity and a firm texture, it's very much for food.</ReviewDescription>
		</Review>
		<Review id="review_119987" taster_id="taster_26" wine_id="wine_85781" points="87">
			<ReviewDescription>Savory dried thyme notes accent sunnier flavors of preserved peach in this brisk, off-dry wine. It's fruity and fresh, with an elegant, sprightly footprint.</ReviewDescription>
		</Review>
		<Review id="review_119988" taster_id="taster_22" wine_id="wine_85782" points="87">
			<ReviewDescription>This has great depth of flavor with its fresh apple and pear fruits and touch of spice. It's off dry while balanced with acidity and a crisp texture. Drink now.</ReviewDescription>
		</Review>
		<Review id="review_119989" taster_id="taster_27" wine_id="wine_85783" points="87">
			<ReviewDescription>Soft, supple plum envelopes an oaky structure in this Cabernet, supported by 15% Merlot. Coffee and chocolate complete the picture, finishing strong at the end, resulting in a value-priced wine of attractive flavor and immediate accessibility.</ReviewDescription>
		</Review>
		<Review id="review_119990" taster_id="taster_22" wine_id="wine_85784" points="87">
			<ReviewDescription>This is a dry wine, very spicy, with a tight, taut texture and strongly mineral character layered with citrus as well as pepper. It's a food wine with its almost crisp aftertaste.</ReviewDescription>
		</Review>
		<Review id="review_119991" taster_id="taster_27" wine_id="wine_85785" points="87">
			<ReviewDescription>Slightly reduced, this wine offers a chalky, tannic backbone to an otherwise juicy explosion of rich black cherry, the whole accented throughout by firm oak and cigar box.</ReviewDescription>
		</Review>
		<Review id="review_119992" taster_id="taster_21" wine_id="wine_85786" points="87">
			<ReviewDescription>This is dominated by oak and oak-driven aromas that include roasted coffee bean, espresso, coconut and vanilla that carry over to the palate, together with plum and chocolate. Astringent, drying tannins give it a rather abrupt finish.</ReviewDescription>
		</Review>
		<Review id="review_119993" taster_id="taster_28" wine_id="wine_85787" points="87">
			<ReviewDescription>Building on 150 years and six generations of winemaking tradition, the winery trends toward a leaner style, with the classic California buttercream aroma cut by tart green apple. In this good everyday sipping wine, flavors that range from pear to barely ripe pineapple prove approachable but not distinctive.</ReviewDescription>
		</Review>
	</Reviews>
</WineReviews>
